skidbilly/__init__.py
skidbilly-1.1.dist-info/METADATA
skidbilly-1.1.dist-info/WHEEL
skidbilly-1.1.dist-info/top_level.txt
skidbilly-1.1.dist-info/RECORD
