Metadata-Version: 2.1
Name: skidbilly
Version: 1.1
Summary: reuploaded
Author-email: <contact@bern.codes>
License: Eclipse Public License 2.0
Keywords: cli,fade,colors,terminal,tui
